saltext/grafana/__init__.py
saltext/grafana/version.py
saltext/grafana/modules/__init__.py
saltext/grafana/modules/grafana4.py
saltext/grafana/states/__init__.py
saltext/grafana/states/grafana.py
saltext/grafana/states/grafana4_dashboard.py
saltext/grafana/states/grafana4_datasource.py
saltext/grafana/states/grafana4_org.py
saltext/grafana/states/grafana4_user.py
saltext/grafana/states/grafana_dashboard.py
saltext/grafana/states/grafana_datasource.py
saltext.grafana-1.0.0.dist-info/LICENSE
saltext.grafana-1.0.0.dist-info/METADATA
saltext.grafana-1.0.0.dist-info/NOTICE
saltext.grafana-1.0.0.dist-info/WHEEL
saltext.grafana-1.0.0.dist-info/entry_points.txt
saltext.grafana-1.0.0.dist-info/top_level.txt
saltext.grafana-1.0.0.dist-info/RECORD
